SpringBootZhongwenWendang152/README.md
SpringBootZhongwenWendang152/__init__.py
SpringBootZhongwenWendang152/__main__.py
SpringBootZhongwenWendang152/file.epub
SpringBootZhongwenWendang152/index.html
SpringBootZhongwenWendang152/css/__init__.py
SpringBootZhongwenWendang152/css/annotations.css
SpringBootZhongwenWendang152/css/main.css
SpringBootZhongwenWendang152/css/normalize.css
SpringBootZhongwenWendang152/css/popup.css
SpringBootZhongwenWendang152/font/__init__.py
SpringBootZhongwenWendang152/font/fontello.eot
SpringBootZhongwenWendang152/font/fontello.svg
SpringBootZhongwenWendang152/font/fontello.ttf
SpringBootZhongwenWendang152/font/fontello.woff
SpringBootZhongwenWendang152/img/__init__.py
SpringBootZhongwenWendang152/img/annotator-glyph-sprite.png
SpringBootZhongwenWendang152/img/annotator-icon-sprite.png
SpringBootZhongwenWendang152/img/apple-touch-icon.png
SpringBootZhongwenWendang152/img/cancelfullscreen.png
SpringBootZhongwenWendang152/img/close.png
SpringBootZhongwenWendang152/img/fullscreen.png
SpringBootZhongwenWendang152/img/loader.gif
SpringBootZhongwenWendang152/img/menu-icon.png
SpringBootZhongwenWendang152/img/save.png
SpringBootZhongwenWendang152/img/saved.png
SpringBootZhongwenWendang152/img/settings-s.png
SpringBootZhongwenWendang152/img/settings.png
SpringBootZhongwenWendang152/img/star.png
SpringBootZhongwenWendang152/js/__init__.py
SpringBootZhongwenWendang152/js/epub.js
SpringBootZhongwenWendang152/js/epub.min.js
SpringBootZhongwenWendang152/js/epub.min.map
SpringBootZhongwenWendang152/js/hooks.min.js
SpringBootZhongwenWendang152/js/hooks.min.map
SpringBootZhongwenWendang152/js/reader.js
SpringBootZhongwenWendang152/js/reader.js.map
SpringBootZhongwenWendang152/js/reader.min.js
SpringBootZhongwenWendang152/js/reader.min.map
SpringBootZhongwenWendang152/js/hooks/__init__.py
SpringBootZhongwenWendang152/js/hooks/extensions/__init__.py
SpringBootZhongwenWendang152/js/hooks/extensions/highlight.js
spring_boot_zhongwen_wendang_1_5_2-2024.3.2.0.dist-info/METADATA
spring_boot_zhongwen_wendang_1_5_2-2024.3.2.0.dist-info/WHEEL
spring_boot_zhongwen_wendang_1_5_2-2024.3.2.0.dist-info/entry_points.txt
spring_boot_zhongwen_wendang_1_5_2-2024.3.2.0.dist-info/top_level.txt
spring_boot_zhongwen_wendang_1_5_2-2024.3.2.0.dist-info/RECORD
